pastecat.py
pastecat-0.0.1.dist-info/LICENSE
pastecat-0.0.1.dist-info/METADATA
pastecat-0.0.1.dist-info/WHEEL
pastecat-0.0.1.dist-info/entry_points.txt
pastecat-0.0.1.dist-info/top_level.txt
pastecat-0.0.1.dist-info/RECORD
