Metadata-Version: 2.1
Name: pastecat
Version: 0.0.1
Summary: Paste clipboard image to file on Windows/macOS.
Home-page: https://github.com/atsuoishimoto/pastecat
Author: Atsuo Ishimoto
License: MIT
Project-URL: Source, https://github.com/atsuoishimoto/pastecat
Platform: UNKNOWN
Classifier: Programming Language :: Python :: 3
Classifier: Programming Language :: Python :: 3.7
Classifier: Programming Language :: Python :: 3.8
Classifier: Development Status :: 4 - Beta
Classifier: Environment :: Console
Classifier: Operating System :: MacOS :: MacOS X
Classifier: Operating System :: Microsoft :: Windows
Classifier: License :: OSI Approved :: MIT License
Requires-Python: >=3.7
Requires-Dist: pillow
Provides-Extra: dev
Requires-Dist: wheel ; extra == 'dev'
Requires-Dist: black ; extra == 'dev'
